COPYING.md
MANIFEST.in
README.md
setup.py
djungle/__init__.py
djungle/hyphenator/__init__.py
djungle/hyphenator/static/.DS_Store
djungle/hyphenator/static/djungle/.DS_Store
djungle/hyphenator/static/djungle/hyphenator/.DS_Store
djungle/hyphenator/static/djungle/hyphenator/hyphenator.full.js
djungle/hyphenator/static/djungle/hyphenator/hyphenator.js
djungle/hyphenator/static/djungle/hyphenator/patterns/be.js
djungle/hyphenator/static/djungle/hyphenator/patterns/bn.js
djungle/hyphenator/static/djungle/hyphenator/patterns/ca.js
djungle/hyphenator/static/djungle/hyphenator/patterns/cs.js
djungle/hyphenator/static/djungle/hyphenator/patterns/da.js
djungle/hyphenator/static/djungle/hyphenator/patterns/de.js
djungle/hyphenator/static/djungle/hyphenator/patterns/el-monoton.js
djungle/hyphenator/static/djungle/hyphenator/patterns/el-polyton.js
djungle/hyphenator/static/djungle/hyphenator/patterns/en-gb.js
djungle/hyphenator/static/djungle/hyphenator/patterns/en-us.js
djungle/hyphenator/static/djungle/hyphenator/patterns/eo.js
djungle/hyphenator/static/djungle/hyphenator/patterns/es.js
djungle/hyphenator/static/djungle/hyphenator/patterns/et.js
djungle/hyphenator/static/djungle/hyphenator/patterns/fi.js
djungle/hyphenator/static/djungle/hyphenator/patterns/fr.js
djungle/hyphenator/static/djungle/hyphenator/patterns/grc.js
djungle/hyphenator/static/djungle/hyphenator/patterns/gu.js
djungle/hyphenator/static/djungle/hyphenator/patterns/hi.js
djungle/hyphenator/static/djungle/hyphenator/patterns/hu.js
djungle/hyphenator/static/djungle/hyphenator/patterns/hy.js
djungle/hyphenator/static/djungle/hyphenator/patterns/it.js
djungle/hyphenator/static/djungle/hyphenator/patterns/kn.js
djungle/hyphenator/static/djungle/hyphenator/patterns/la.js
djungle/hyphenator/static/djungle/hyphenator/patterns/lt.js
djungle/hyphenator/static/djungle/hyphenator/patterns/lv.js
djungle/hyphenator/static/djungle/hyphenator/patterns/ml.js
djungle/hyphenator/static/djungle/hyphenator/patterns/nb-no.js
djungle_hyphenator.egg-info/PKG-INFO
djungle_hyphenator.egg-info/SOURCES.txt
djungle_hyphenator.egg-info/dependency_links.txt
djungle_hyphenator.egg-info/namespace_packages.txt
djungle_hyphenator.egg-info/not-zip-safe
djungle_hyphenator.egg-info/requires.txt
djungle_hyphenator.egg-info/top_level.txt